elexmodel/__init__.py
elexmodel/cli.py
elexmodel/client.py
elexmodel/logger.py
elexmodel/distributions/GaussianModel.py
elexmodel/distributions/__init__.py
elexmodel/handlers/__init__.py
elexmodel/handlers/config.py
elexmodel/handlers/s3.py
elexmodel/handlers/data/CombinedData.py
elexmodel/handlers/data/Estimandizer.py
elexmodel/handlers/data/Featurizer.py
elexmodel/handlers/data/LiveData.py
elexmodel/handlers/data/ModelResults.py
elexmodel/handlers/data/PreprocessedData.py
elexmodel/handlers/data/VersionedData.py
elexmodel/handlers/data/__init__.py
elexmodel/models/BaseElectionModel.py
elexmodel/models/BootstrapElectionModel.py
elexmodel/models/ConformalElectionModel.py
elexmodel/models/GaussianElectionModel.py
elexmodel/models/NonparametricElectionModel.py
elexmodel/models/__init__.py
elexmodel/utils/__init__.py
elexmodel/utils/constants.py
elexmodel/utils/file_utils.py
elexmodel/utils/math_utils.py
elexmodel/utils/pandas_utils.py
elex_model-2.2.5.dist-info/METADATA
elex_model-2.2.5.dist-info/WHEEL
elex_model-2.2.5.dist-info/entry_points.txt
elex_model-2.2.5.dist-info/top_level.txt
elex_model-2.2.5.dist-info/RECORD
