Metadata-Version: 2.1
Name: elex-model
Version: 2.2.5
Summary: A package for the Washington Post's live election night model
License: MIT
Classifier: Intended Audience :: Developers
Classifier: License :: OSI Approved :: MIT License
Classifier: Programming Language :: Python
Classifier: Programming Language :: Python :: 3.10
Classifier: Programming Language :: Python :: 3.11
Requires-Dist: click >=8.1
Requires-Dist: elex-solver >=2.1.1
Requires-Dist: pandas >=2.2
Requires-Dist: boto3 >=1.34
Requires-Dist: python-dotenv >=1.0
Requires-Dist: scipy >=1.14
Requires-Dist: s3transfer >=0.9.0
Requires-Dist: botocore >=1.34.162
